pycim/__init__.py
pycim/analyzer.py
pycim/competitor.py
pycim/sampler.py
pycim/simulation/__init__.py
pycim/simulation/device.py
pycim/simulation/setup.py
pycim/simulation/simulate.py
pycim/simulation/solver.py
pycim/simulation/model/__init__.py
pycim/simulation/model/c_number.py
pycim/simulation/model/discrete.py
pycim/simulation/model/meanField.py
pycim/utils/__init__.py
pycim/utils/bias.py
pycim/utils/const.py
pycim/utils/file_J.py
pycim/utils/getIsingEnergy.py
pycim/utils/param_optimizer.py
pycim_simulator-0.1.4.dist-info/METADATA
pycim_simulator-0.1.4.dist-info/WHEEL
pycim_simulator-0.1.4.dist-info/top_level.txt
pycim_simulator-0.1.4.dist-info/RECORD
