Metadata-Version: 2.4
Name: pycim-simulator
Version: 0.1.4
Summary: A Python Framework for the Dynamics of Coherent Ising Machine
Home-page: https://github.com/shadowforwind/pycim-simulator
Author: peixiangli
Author-email: peixiangli@quanta.org.cn
Classifier: Programming Language :: Python :: 3
Classifier: License :: OSI Approved :: MIT License
Classifier: Operating System :: OS Independent
Requires-Python: >=3.7.7
Dynamic: author
Dynamic: author-email
Dynamic: classifier
Dynamic: description
Dynamic: description-content-type
Dynamic: home-page
Dynamic: requires-python
Dynamic: summary
